examples/miniproj3/memory.sv
module memory #(
    parameter INIT_FILE = ""
)(
    input logic clk,
    input logic [8:0] read_address,
    output logic [9:0] read_data
);

    logic [8:0] quarter_cycle_memory [0:127]; // 9-bit amplitude (0-511)

    initial if (INIT_FILE) begin
        $readmemh(INIT_FILE, quarter_cycle_memory);
    end

    always_ff @(posedge clk) begin
        case (read_address[8:7])
            // Q1: 0-π/2 -> 512 to 1023 (512 + amplitude)
            2'b00: read_data <= 10'd512 + {1'b0, quarter_cycle_memory[read_address[6:0]]};
            
            // Q2: π/2-π -> 1023 to 512 (512 + mirrored amplitude)
            2'b01: read_data <= 10'd512 + {1'b0, quarter_cycle_memory[127 - read_address[6:0]]};
            
            // Q3: π-3π/2 -> 512 to 1 (512 - amplitude)
            2'b10: read_data <= 10'd512 - {1'b0, quarter_cycle_memory[read_address[6:0]]};
            
            // Q4: 3π/2-2π -> 1 to 512 (512 - mirrored amplitude)
            2'b11: read_data <= 10'd512 - {1'b0, quarter_cycle_memory[127 - read_address[6:0]]};
        endcase
    end

endmodule

examples/miniproj3/sine.sv
`include "memory.sv"

// Sine Wave Top-Level Module

module top(
    input logic     clk, 
    output logic    _9b,    // D0
    output logic    _6a,    // D1
    output logic    _4a,    // D2
    output logic    _2a,    // D3
    output logic    _0a,    // D4
    output logic    _5a,    // D5
    output logic    _3b,    // D6
    output logic    _49a,   // D7
    output logic    _45a,   // D8
    output logic    _48b    // D9
);

    logic [8:0] address = 0;
    logic [9:0] data;

    memory #(
        .INIT_FILE      ("sine.txt") // Uses only 128 samples
    ) u1 (
        .clk            (clk), 
        .read_address   (address), 
        .read_data      (data)
    );

    always_ff @(posedge clk) begin
        address <= address + 1;
    end

    assign {_48b, _45a, _49a, _3b, _5a, _0a, _2a, _4a, _6a, _9b} = data;

endmodule

examples/miniproj3/sine_tb.sv
`timescale 10ns/10ns
`include "sine.sv"

module sine_tb;

    logic clk = 0;
    logic _9b, _6a, _4a, _2a, _0a, _5a, _3b, _49a, _45a, _48b;

    top u0 (
        .clk    (clk), 
        ._9b    (_9b), 
        ._6a    (_6a), 
        ._4a    (_4a), 
        ._2a    (_2a), 
        ._0a    (_0a), 
        ._5a    (_5a), 
        ._3b    (_3b), 
        ._49a   (_49a), 
        ._45a   (_45a), 
        ._48b   (_48b)
    );

    initial begin
        $dumpfile("sine.vcd");
        $dumpvars(0, sine_tb);

        // Debugging: Monitor values every cycle
        $monitor("Time: %0t | _9b: %b _6a: %b _4a: %b _2a: %b _0a: %b _5a: %b _3b: %b _49a: %b _45a: %b _48b: %b", 
                  $time, _9b, _6a, _4a, _2a, _0a, _5a, _3b, _49a, _45a, _48b);

        #10000
        $finish;
    end

    always begin
        #4
        clk = ~clk;
    end

endmodule

examples/miniproj3/sine.vcd
$date
	Sun Mar 09 21:21:32 2025
$end
$version
	Icarus Verilog
$end
$timescale
	10ns
$end
$scope module sine_tb $end
$var wire 1 ! _9b $end
$var wire 1 " _6a $end
$var wire 1 # _5a $end
$var wire 1 $ _4a $end
$var wire 1 % _49a $end
$var wire 1 & _48b $end
$var wire 1 ' _45a $end
$var wire 1 ( _3b $end
$var wire 1 ) _2a $end
$var wire 1 * _0a $end
$var reg 1 + clk $end
$scope module u0 $end
$var wire 1 + clk $end
$var wire 10 , data [9:0] $end
$var wire 1 ! _9b $end
$var wire 1 " _6a $end
$var wire 1 # _5a $end
$var wire 1 $ _4a $end
$var wire 1 % _49a $end
$var wire 1 & _48b $end
$var wire 1 ' _45a $end
$var wire 1 ( _3b $end
$var wire 1 ) _2a $end
$var wire 1 * _0a $end
$var reg 9 - address [8:0] $end
$scope module u1 $end
$var wire 1 + clk $end
$var wire 9 . read_address [8:0] $end
$var parameter 64 / INIT_FILE $end
$var reg 10 0 read_data [9:0] $end
$upscope $end
$upscope $end
$upscope $end
$enddefinitions $end
$comment Show the parameter values. $end
$dumpall
b111001101101001011011100110010100101110011101000111100001110100 /
$end
#0
$dumpvars
bx 0
b0 .
b0 -
bx ,
0+
x*
x)
x(
x'
x&
x%
x$
x#
x"
x!
$end
#4
1&
0'
0%
0(
0#
0*
0)
0$
0"
0!
b1000000000 ,
b1000000000 0
b1 -
b1 .
1+
#8
0+
#12
1$
1"
b10 -
b10 .
b1000000110 ,
b1000000110 0
1+
#16
0+
#20
1)
0"
b1000001100 ,
b1000001100 0
b11 -
b11 .
1+
#24
0+
#28
1*
0)
0$
1"
b100 -
b100 .
b1000010010 ,
b1000010010 0
1+
#32
0+
#36
1)
0"
1!
b1000011001 ,
b1000011001 0
b101 -
b101 .
1+
#40
0+
#44
1$
1"
b110 -
b110 .
b1000011111 ,
b1000011111 0
1+
#48
0+
#52
1#
0*
0)
0"
b1000100101 ,
b1000100101 0
b111 -
b111 .
1+
#56
0+
#60
1)
0$
1"
b1000 -
b1000 .
b1000101011 ,
b1000101011 0
1+
#64
0+
#68
1*
0)
0!
b1000110010 ,
b1000110010 0
b1001 -
b1001 .
1+
#72
0+
#76
1)
0"
b1010 -
b1010 .
b1000111000 ,
b1000111000 0
1+
#80
0+
#84
1$
1"
b1000111110 ,
b1000111110 0
b1011 -
b1011 .
1+
#88
0+
#92
1(
0#
0*
0)
0"
b1100 -
b1100 .
b1001000100 ,
b1001000100 0
1+
#96
0+
#100
1)
0$
1"
1!
b1001001011 ,
b1001001011 0
b1101 -
b1101 .
1+
#104
0+
#108
1*
0)
0"
b1110 -
b1110 .
b1001010001 ,
b1001010001 0
1+
#112
0+
#116
1$
1"
b1001010111 ,
b1001010111 0
b1111 -
b1111 .
1+
#120
0+
#124
1)
0"
b10000 -
b10000 .
b1001011101 ,
b1001011101 0
1+
#128
0+
#132
1#
0*
0)
0$
1"
b1001100011 ,
b1001100011 0
b10001 -
b10001 .
1+
#136
0+
#140
1)
0"
b10010 -
b10010 .
b1001101001 ,
b1001101001 0
1+
#144
0+
#148
1*
0)
0!
b1001110000 ,
b1001110000 0
b10011 -
b10011 .
1+
#152
0+
#156
1$
1"
b10100 -
b10100 .
b1001110110 ,
b1001110110 0
1+
#160
0+
#164
1)
0"
b1001111100 ,
b1001111100 0
b10101 -
b10101 .
1+
#168
0+
#172
1%
0(
0#
0*
0)
0$
1"
b10110 -
b10110 .
b1010000010 ,
b1010000010 0
1+
#176
0+
#180
1)
0"
b1010001000 ,
b1010001000 0
b10111 -
b10111 .
1+
#184
0+
#188
1$
1"
b11000 -
b11000 .
b1010001110 ,
b1010001110 0
1+
#192
0+
#196
1*
0)
0"
b1010010100 ,
b1010010100 0
b11001 -
b11001 .
1+
#200
0+
#204
1)
0$
1"
b11010 -
b11010 .
b1010011010 ,
b1010011010 0
1+
#208
0+
#212
1#
0*
0)
0"
b1010100000 ,
b1010100000 0
b11011 -
b11011 .
1+
#216
0+
#220
1$
1"
b11100 -
b11100 .
b1010100110 ,
b1010100110 0
1+
#224
0+
#228
1)
0"
b1010101100 ,
b1010101100 0
b11101 -
b11101 .
1+
#232
0+
#236
1*
0)
0$
1"
b11110 -
b11110 .
b1010110010 ,
b1010110010 0
1+
#240
0+
#244
1)
0"
b1010111000 ,
b1010111000 0
b11111 -
b11111 .
1+
#248
0+
#252
1$
1!
b100000 -
b100000 .
b1010111101 ,
b1010111101 0
1+
#256
0+
#260
1(
0#
0*
0)
0$
1"
b1011000011 ,
b1011000011 0
b100001 -
b100001 .
1+
#264
0+
#268
1)
0"
b100010 -
b100010 .
b1011001001 ,
b1011001001 0
1+
#272
0+
#276
1$
1"
b1011001111 ,
b1011001111 0
b100011 -
b100011 .
1+
#280
0+
#284
1*
0)
0"
b100100 -
b100100 .
b1011010101 ,
b1011010101 0
1+
#288
0+
#292
1)
0$
1"
0!
b1011011010 ,
b1011011010 0
b100101 -
b100101 .
1+
#296
0+
#300
1#
0*
0)
0"
b100110 -
b100110 .
b1011100000 ,
b1011100000 0
1+
#304
0+
#308
1$
1!
b1011100101 ,
b1011100101 0
b100111 -
b100111 .
1+
#312
0+
#316
1)
0$
1"
b101000 -
b101000 .
b1011101011 ,
b1011101011 0
1+
#320
0+
#324
1*
0)
0"
b1011110001 ,
b1011110001 0
b101001 -
b101001 .
1+
#328
0+
#332
1$
1"
0!
b101010 -
b101010 .
b1011110110 ,
b1011110110 0
1+
#336
0+
#340
1)
0"
b1011111100 ,
b1011111100 0
b101011 -
b101011 .
1+
#344
0+
#348
1'
0%
0(
0#
0*
0)
0$
1!
b101100 -
b101100 .
b1100000001 ,
b1100000001 0
1+
#352
0+
#356
1$
1"
0!
b1100000110 ,
b1100000110 0
b101101 -
b101101 .
1+
#360
0+
#364
1)
0"
b101110 -
b101110 .
b1100001100 ,
b1100001100 0
1+
#368
0+
#372
1*
0)
0$
1!
b1100010001 ,
b1100010001 0
b101111 -
b101111 .
1+
#376
0+
#380
1$
1"
0!
b110000 -
b110000 .
b1100010110 ,
b1100010110 0
1+
#384
0+
#388
1)
0"
b1100011100 ,
b1100011100 0
b110001 -
b110001 .
1+
#392
0+
#396
1#
0*
0)
0$
1!
b110010 -
b110010 .
b1100100001 ,
b1100100001 0
1+
#400
0+
#404
1$
1"
0!
b1100100110 ,
b1100100110 0
b110011 -
b110011 .
1+
#408
0+
#412
1)
0$
1!
b110100 -
b110100 .
b1100101011 ,
b1100101011 0
1+
#416
0+
#420
1*
0)
0"
0!
b1100110000 ,
b1100110000 0
b110101 -
b110101 .
1+
#424
0+
#428
1$
1!
b110110 -
b110110 .
b1100110101 ,
b1100110101 0
1+
#432
0+
#436
1)
0$
1"
0!
b1100111010 ,
b1100111010 0
b110111 -
b110111 .
1+
#440
0+
#444
1$
1!
b111000 -
b111000 .
b1100111111 ,
b1100111111 0
1+
#448
0+
#452
1(
0#
0*
0)
0"
0!
b1101000100 ,
b1101000100 0
b111001 -
b111001 .
1+
#456
0+
#460
1)
0$
1!
b111010 -
b111010 .
b1101001001 ,
b1101001001 0
1+
#464
0+
#468
1$
1"
0!
b1101001110 ,
b1101001110 0
b111011 -
b111011 .
1+
#472
0+
#476
1*
0)
0$
b111100 -
b111100 .
b1101010010 ,
b1101010010 0
1+
#480
0+
#484
1$
1!
b1101010111 ,
b1101010111 0
b111101 -
b111101 .
1+
#488
0+
#492
1)
0"
0!
b111110 -
b111110 .
b1101011100 ,
b1101011100 0
1+
#496
0+
#500
1#
0*
0)
0$
b1101100000 ,
b1101100000 0
b111111 -
b111111 .
1+
#504
0+
#508
1$
1!
b1000000 -
b1000000 .
b1101100101 ,
b1101100101 0
1+
#512
0+
#516
1)
0$
b1101101001 ,
b1101101001 0
b1000001 -
b1000001 .
1+
#520
0+
#524
1$
1"
0!
b1000010 -
b1000010 .
b1101101110 ,
b1101101110 0
1+
#528
0+
#532
1*
0)
0$
b1101110010 ,
b1101110010 0
b1000011 -
b1000011 .
1+
#536
0+
#540
1$
b1000100 -
b1000100 .
b1101110110 ,
b1101110110 0
1+
#544
0+
#548
1)
0$
b1101111010 ,
b1101111010 0
b1000101 -
b1000101 .
1+
#552
0+
#556
1$
1!
b1000110 -
b1000110 .
b1101111111 ,
b1101111111 0
1+
#560
0+
#564
1%
0(
0#
0*
0)
0$
b1110000011 ,
b1110000011 0
b1000111 -
b1000111 .
1+
#568
0+
#572
1$
b1001000 -
b1001000 .
b1110000111 ,
b1110000111 0
1+
#576
0+
#580
1)
0$
b1110001011 ,
b1110001011 0
b1001001 -
b1001001 .
1+
#584
0+
#588
1$
b1001010 -
b1001010 .
b1110001111 ,
b1110001111 0
1+
#592
0+
#596
1*
0)
0$
b1110010011 ,
b1110010011 0
b1001011 -
b1001011 .
1+
#600
0+
#604
1$
b1001100 -
b1001100 .
b1110010111 ,
b1110010111 0
1+
#608
0+
#612
1)
0$
0!
b1110011010 ,
b1110011010 0
b1001101 -
b1001101 .
1+
#616
0+
#620
1$
b1001110 -
b1001110 .
b1110011110 ,
b1110011110 0
1+
#624
0+
#628
1#
0*
0)
0$
b1110100010 ,
b1110100010 0
b1001111 -
b1001111 .
1+
#632
0+
#636
1$
0"
1!
b1010000 -
b1010000 .
b1110100101 ,
b1110100101 0
1+
#640
0+
#644
1)
0$
b1110101001 ,
b1110101001 0
b1010001 -
b1010001 .
1+
#648
0+
#652
1$
0!
b1010010 -
b1010010 .
b1110101100 ,
b1110101100 0
1+
#656
0+
#660
1*
0)
0$
b1110110000 ,
b1110110000 0
b1010011 -
b1010011 .
1+
#664
0+
#668
1"
1!
b1010100 -
b1010100 .
b1110110011 ,
b1110110011 0
1+
#672
0+
#676
1$
0!
b1110110110 ,
b1110110110 0
b1010101 -
b1010101 .
1+
#680
0+
#684
1)
0$
0"
1!
b1010110 -
b1010110 .
b1110111001 ,
b1110111001 0
1+
#688
0+
#692
1$
b1110111101 ,
b1110111101 0
b1010111 -
b1010111 .
1+
#696
0+
#700
1(
0#
0*
0)
0$
0!
b1011000 -
b1011000 .
b1111000000 ,
b1111000000 0
1+
#704
0+
#708
1"
1!
b1111000011 ,
b1111000011 0
b1011001 -
b1011001 .
1+
#712
0+
#716
1$
0!
b1011010 -
b1011010 .
b1111000110 ,
b1111000110 0
1+
#720
0+
#724
1)
0$
0"
b1111001000 ,
b1111001000 0
b1011011 -
b1011011 .
1+
#728
0+
#732
1"
1!
b1011100 -
b1011100 .
b1111001011 ,
b1111001011 0
1+
#736
0+
#740
1$
0!
b1111001110 ,
b1111001110 0
b1011101 -
b1011101 .
1+
#744
0+
#748
1*
0)
0$
0"
1!
b1011110 -
b1011110 .
b1111010001 ,
b1111010001 0
1+
#752
0+
#756
1"
b1111010011 ,
b1111010011 0
b1011111 -
b1011111 .
1+
#760
0+
#764
1$
0!
b1100000 -
b1100000 .
b1111010110 ,
b1111010110 0
1+
#768
0+
#772
1)
0$
0"
b1111011000 ,
b1111011000 0
b1100001 -
b1100001 .
1+
#776
0+
#780
1"
b1100010 -
b1100010 .
b1111011010 ,
b1111011010 0
1+
#784
0+
#788
1$
0"
1!
b1111011101 ,
b1111011101 0
b1100011 -
b1100011 .
1+
#792
0+
#796
1"
b1100100 -
b1100100 .
b1111011111 ,
b1111011111 0
1+
#800
0+
#804
1#
0*
0)
0$
0"
b1111100001 ,
b1111100001 0
b1100101 -
b1100101 .
1+
#808
0+
#812
1"
b1100110 -
b1100110 .
b1111100011 ,
b1111100011 0
1+
#816
0+
#820
1$
0"
b1111100101 ,
b1111100101 0
b1100111 -
b1100111 .
1+
#824
0+
#828
1"
b1101000 -
b1101000 .
b1111100111 ,
b1111100111 0
1+
#832
0+
#836
1)
0$
0"
b1111101001 ,
b1111101001 0
b1101001 -
b1101001 .
1+
#840
0+
#844
1"
b1101010 -
b1101010 .
b1111101011 ,
b1111101011 0
1+
#848
0+
#852
1$
0"
0!
b1111101100 ,
b1111101100 0
b1101011 -
b1101011 .
1+
#856
0+
#860
1"
b1101100 -
b1101100 .
b1111101110 ,
b1111101110 0
1+
#864
0+
#868
1*
0)
0$
0"
b1111110000 ,
b1111110000 0
b1101101 -
b1101101 .
1+
#872
0+
#876
1!
b1101110 -
b1101110 .
b1111110001 ,
b1111110001 0
1+
#880
0+
#884
1"
b1111110011 ,
b1111110011 0
b1101111 -
b1101111 .
1+
#888
0+
#892
1$
0"
0!
b1110000 -
b1110000 .
b1111110100 ,
b1111110100 0
1+
#896
0+
#900
1!
b1111110101 ,
b1111110101 0
b1110001 -
b1110001 .
1+
#904
0+
#908
1"
0!
b1110010 -
b1110010 .
b1111110110 ,
b1111110110 0
1+
#912
0+
#916
1!
b1111110111 ,
b1111110111 0
b1110011 -
b1110011 .
1+
#920
0+
#924
1)
0$
0"
b1110100 -
b1110100 .
b1111111001 ,
b1111111001 0
1+
#928
0+
#932
b1110101 -
b1110101 .
1+
#936
0+
#940
1"
0!
b1110110 -
b1110110 .
b1111111010 ,
b1111111010 0
1+
#944
0+
#948
1!
b1111111011 ,
b1111111011 0
b1110111 -
b1110111 .
1+
#952
0+
#956
1$
0"
0!
b1111000 -
b1111000 .
b1111111100 ,
b1111111100 0
1+
#960
0+
#964
1!
b1111111101 ,
b1111111101 0
b1111001 -
b1111001 .
1+
#968
0+
#972
b1111010 -
b1111010 .
1+
#976
0+
#980
1"
0!
b1111111110 ,
b1111111110 0
b1111011 -
b1111011 .
1+
#984
0+
#988
b1111100 -
b1111100 .
1+
#992
0+
#996
b1111101 -
b1111101 .
1+
#1000
0+
#1004
1!
b1111110 -
b1111110 .
b1111111111 ,
b1111111111 0
1+
#1008
0+
#1012
b1111111 -
b1111111 .
1+
#1016
0+
#1020
b10000000 -
b10000000 .
1+
#1024
0+
#1028
b10000001 -
b10000001 .
1+
#1032
0+
#1036
b10000010 -
b10000010 .
1+
#1040
0+
#1044
b10000011 -
b10000011 .
1+
#1048
0+
#1052
0!
b10000100 -
b10000100 .
b1111111110 ,
b1111111110 0
1+
#1056
0+
#1060
b10000101 -
b10000101 .
1+
#1064
0+
#1068
b10000110 -
b10000110 .
1+
#1072
0+
#1076
0"
1!
b1111111101 ,
b1111111101 0
b10000111 -
b10000111 .
1+
#1080
0+
#1084
b10001000 -
b10001000 .
1+
#1088
0+
#1092
0!
b1111111100 ,
b1111111100 0
b10001001 -
b10001001 .
1+
#1096
0+
#1100
0$
1"
1!
b10001010 -
b10001010 .
b1111111011 ,
b1111111011 0
1+
#1104
0+
#1108
0!
b1111111010 ,
b1111111010 0
b10001011 -
b10001011 .
1+
#1112
0+
#1116
0"
1!
b10001100 -
b10001100 .
b1111111001 ,
b1111111001 0
1+
#1120
0+
#1124
b10001101 -
b10001101 .
1+
#1128
0+
#1132
0)
1$
1"
b10001110 -
b10001110 .
b1111110111 ,
b1111110111 0
1+
#1136
0+
#1140
0!
b1111110110 ,
b1111110110 0
b10001111 -
b10001111 .
1+
#1144
0+
#1148
0"
1!
b10010000 -
b10010000 .
b1111110101 ,
b1111110101 0
1+
#1152
0+
#1156
0!
b1111110100 ,
b1111110100 0
b10010001 -
b10010001 .
1+
#1160
0+
#1164
0$
1"
1!
b10010010 -
b10010010 .
b1111110011 ,
b1111110011 0
1+
#1168
0+
#1172
0"
b1111110001 ,
b1111110001 0
b10010011 -
b10010011 .
1+
#1176
0+
#1180
0!
b10010100 -
b10010100 .
b1111110000 ,
b1111110000 0
1+
#1184
0+
#1188
0*
1)
1$
1"
b1111101110 ,
b1111101110 0
b10010101 -
b10010101 .
1+
#1192
0+
#1196
0"
b10010110 -
b10010110 .
b1111101100 ,
b1111101100 0
1+
#1200
0+
#1204
0$
1"
1!
b1111101011 ,
b1111101011 0
b10010111 -
b10010111 .
1+
#1208
0+
#1212
0"
b10011000 -
b10011000 .
b1111101001 ,
b1111101001 0
1+
#1216
0+
#1220
0)
1$
1"
b1111100111 ,
b1111100111 0
b10011001 -
b10011001 .
1+
#1224
0+
#1228
0"
b10011010 -
b10011010 .
b1111100101 ,
b1111100101 0
1+
#1232
0+
#1236
0$
1"
b1111100011 ,
b1111100011 0
b10011011 -
b10011011 .
1+
#1240
0+
#1244
0"
b10011100 -
b10011100 .
b1111100001 ,
b1111100001 0
1+
#1248
0+
#1252
0#
1*
1)
1$
1"
b1111011111 ,
b1111011111 0
b10011101 -
b10011101 .
1+
#1256
0+
#1260
0"
b10011110 -
b10011110 .
b1111011101 ,
b1111011101 0
1+
#1264
0+
#1268
0$
1"
0!
b1111011010 ,
b1111011010 0
b10011111 -
b10011111 .
1+
#1272
0+
#1276
0"
b10100000 -
b10100000 .
b1111011000 ,
b1111011000 0
1+
#1280
0+
#1284
0)
1$
1"
b1111010110 ,
b1111010110 0
b10100001 -
b10100001 .
1+
#1288
0+
#1292
0$
1!
b10100010 -
b10100010 .
b1111010011 ,
b1111010011 0
1+
#1296
0+
#1300
0"
b1111010001 ,
b1111010001 0
b10100011 -
b10100011 .
1+
#1304
0+
#1308
0*
1)
1$
1"
0!
b10100100 -
b10100100 .
b1111001110 ,
b1111001110 0
1+
#1312
0+
#1316
0$
1!
b1111001011 ,
b1111001011 0
b10100101 -
b10100101 .
1+
#1320
0+
#1324
0"
0!
b10100110 -
b10100110 .
b1111001000 ,
b1111001000 0
1+
#1328
0+
#1332
0)
1$
1"
b1111000110 ,
b1111000110 0
b10100111 -
b10100111 .
1+
#1336
0+
#1340
0$
1!
b10101000 -
b10101000 .
b1111000011 ,
b1111000011 0
1+
#1344
0+
#1348
0"
0!
b1111000000 ,
b1111000000 0
b10101001 -
b10101001 .
1+
#1352
0+
#1356
0(
1#
1*
1)
1$
1!
b10101010 -
b10101010 .
b1110111101 ,
b1110111101 0
1+
#1360
0+
#1364
0$
b1110111001 ,
b1110111001 0
b10101011 -
b10101011 .
1+
#1368
0+
#1372
0)
1$
1"
0!
b10101100 -
b10101100 .
b1110110110 ,
b1110110110 0
1+
#1376
0+
#1380
0$
1!
b1110110011 ,
b1110110011 0
b10101101 -
b10101101 .
1+
#1384
0+
#1388
0"
0!
b10101110 -
b10101110 .
b1110110000 ,
b1110110000 0
1+
#1392
0+
#1396
0*
1)
1$
b1110101100 ,
b1110101100 0
b10101111 -
b10101111 .
1+
#1400
0+
#1404
0$
1!
b10110000 -
b10110000 .
b1110101001 ,
b1110101001 0
1+
#1408
0+
#1412
0)
1$
b1110100101 ,
b1110100101 0
b10110001 -
b10110001 .
1+
#1416
0+
#1420
0$
1"
0!
b10110010 -
b10110010 .
b1110100010 ,
b1110100010 0
1+
#1424
0+
#1428
0#
1*
1)
1$
b1110011110 ,
b1110011110 0
b10110011 -
b10110011 .
1+
#1432
0+
#1436
0$
b10110100 -
b10110100 .
b1110011010 ,
b1110011010 0
1+
#1440
0+
#1444
0)
1$
1!
b1110010111 ,
b1110010111 0
b10110101 -
b10110101 .
1+
#1448
0+
#1452
0$
b10110110 -
b10110110 .
b1110010011 ,
b1110010011 0
1+
#1456
0+
#1460
0*
1)
1$
b1110001111 ,
b1110001111 0
b10110111 -
b10110111 .
1+
#1464
0+
#1468
0$
b10111000 -
b10111000 .
b1110001011 ,
b1110001011 0
1+
#1472
0+
#1476
0)
1$
b1110000111 ,
b1110000111 0
b10111001 -
b10111001 .
1+
#1480
0+
#1484
0$
b10111010 -
b10111010 .
b1110000011 ,
b1110000011 0
1+
#1488
0+
#1492
0%
1(
1#
1*
1)
1$
b1101111111 ,
b1101111111 0
b10111011 -
b10111011 .
1+
#1496
0+
#1500
0$
0!
b10111100 -
b10111100 .
b1101111010 ,
b1101111010 0
1+
#1504
0+
#1508
0)
1$
b1101110110 ,
b1101110110 0
b10111101 -
b10111101 .
1+
#1512
0+
#1516
0$
b10111110 -
b10111110 .
b1101110010 ,
b1101110010 0
1+
#1520
0+
#1524
0*
1)
1$
b1101101110 ,
b1101101110 0
b10111111 -
b10111111 .
1+
#1528
0+
#1532
0$
0"
1!
b11000000 -
b11000000 .
b1101101001 ,
b1101101001 0
1+
#1536
0+
#1540
0)
1$
b1101100101 ,
b1101100101 0
b11000001 -
b11000001 .
1+
#1544
0+
#1548
0$
0!
b11000010 -
b11000010 .
b1101100000 ,
b1101100000 0
1+
#1552
0+
#1556
0#
1*
1)
1$
b1101011100 ,
b1101011100 0
b11000011 -
b11000011 .
1+
#1560
0+
#1564
0)
1"
1!
b11000100 -
b11000100 .
b1101010111 ,
b1101010111 0
1+
#1568
0+
#1572
0$
0!
b1101010010 ,
b1101010010 0
b11000101 -
b11000101 .
1+
#1576
0+
#1580
0*
1)
1$
b11000110 -
b11000110 .
b1101001110 ,
b1101001110 0
1+
#1584
0+
#1588
0$
0"
1!
b1101001001 ,
b1101001001 0
b11000111 -
b11000111 .
1+
#1592
0+
#1596
0)
1$
0!
b11001000 -
b11001000 .
b1101000100 ,
b1101000100 0
1+
#1600
0+
#1604
0(
1#
1*
1)
1"
1!
b1100111111 ,
b1100111111 0
b11001001 -
b11001001 .
1+
#1608
0+
#1612
0$
0!
b11001010 -
b11001010 .
b1100111010 ,
b1100111010 0
1+
#1616
0+
#1620
0)
1$
0"
1!
b1100110101 ,
b1100110101 0
b11001011 -
b11001011 .
1+
#1624
0+
#1628
0$
0!
b11001100 -
b11001100 .
b1100110000 ,
b1100110000 0
1+
#1632
0+
#1636
0*
1)
1"
1!
b1100101011 ,
b1100101011 0
b11001101 -
b11001101 .
1+
#1640
0+
#1644
0)
1$
0!
b11001110 -
b11001110 .
b1100100110 ,
b1100100110 0
1+
#1648
0+
#1652
0$
0"
1!
b1100100001 ,
b1100100001 0
b11001111 -
b11001111 .
1+
#1656
0+
#1660
0#
1*
1)
1$
0!
b11010000 -
b11010000 .
b1100011100 ,
b1100011100 0
1+
#1664
0+
#1668
0)
1"
b1100010110 ,
b1100010110 0
b11010001 -
b11010001 .
1+
#1672
0+
#1676
0$
0"
1!
b11010010 -
b11010010 .
b1100010001 ,
b1100010001 0
1+
#1680
0+
#1684
0*
1)
1$
0!
b1100001100 ,
b1100001100 0
b11010011 -
b11010011 .
1+
#1688
0+
#1692
0)
1"
b11010100 -
b11010100 .
b1100000110 ,
b1100000110 0
1+
#1696
0+
#1700
0$
0"
1!
b1100000001 ,
b1100000001 0
b11010101 -
b11010101 .
1+
#1704
0+
#1708
0'
1%
1(
1#
1*
1)
1$
0!
b11010110 -
b11010110 .
b1011111100 ,
b1011111100 0
1+
#1712
0+
#1716
0)
1"
b1011110110 ,
b1011110110 0
b11010111 -
b11010111 .
1+
#1720
0+
#1724
0$
0"
1!
b11011000 -
b11011000 .
b1011110001 ,
b1011110001 0
1+
#1728
0+
#1732
0*
1)
1"
b1011101011 ,
b1011101011 0
b11011001 -
b11011001 .
1+
#1736
0+
#1740
0)
1$
0"
b11011010 -
b11011010 .
b1011100101 ,
b1011100101 0
1+
#1744
0+
#1748
0$
0!
b1011100000 ,
b1011100000 0
b11011011 -
b11011011 .
1+
#1752
0+
#1756
0#
1*
1)
1"
b11011100 -
b11011100 .
b1011011010 ,
b1011011010 0
1+
#1760
0+
#1764
0)
1$
0"
1!
b1011010101 ,
b1011010101 0
b11011101 -
b11011101 .
1+
#1768
0+
#1772
0*
1)
1"
b11011110 -
b11011110 .
b1011001111 ,
b1011001111 0
1+
#1776
0+
#1780
0$
0"
b1011001001 ,
b1011001001 0
b11011111 -
b11011111 .
1+
#1784
0+
#1788
0)
1"
b11100000 -
b11100000 .
b1011000011 ,
b1011000011 0
1+
#1792
0+
#1796
0(
1#
1*
1)
1$
0"
b1010111101 ,
b1010111101 0
b11100001 -
b11100001 .
1+
#1800
0+
#1804
0$
0!
b11100010 -
b11100010 .
b1010111000 ,
b1010111000 0
1+
#1808
0+
#1812
0)
1"
b1010110010 ,
b1010110010 0
b11100011 -
b11100011 .
1+
#1816
0+
#1820
0*
1)
1$
0"
b11100100 -
b11100100 .
b1010101100 ,
b1010101100 0
1+
#1824
0+
#1828
0)
1"
b1010100110 ,
b1010100110 0
b11100101 -
b11100101 .
1+
#1832
0+
#1836
0$
0"
b11100110 -
b11100110 .
b1010100000 ,
b1010100000 0
1+
#1840
0+
#1844
0#
1*
1)
1"
b1010011010 ,
b1010011010 0
b11100111 -
b11100111 .
1+
#1848
0+
#1852
0)
1$
0"
b11101000 -
b11101000 .
b1010010100 ,
b1010010100 0
1+
#1856
0+
#1860
0*
1)
1"
b1010001110 ,
b1010001110 0
b11101001 -
b11101001 .
1+
#1864
0+
#1868
0$
0"
b11101010 -
b11101010 .
b1010001000 ,
b1010001000 0
1+
#1872
0+
#1876
0)
1"
b1010000010 ,
b1010000010 0
b11101011 -
b11101011 .
1+
#1880
0+
#1884
0%
1(
1#
1*
1)
1$
0"
b11101100 -
b11101100 .
b1001111100 ,
b1001111100 0
1+
#1888
0+
#1892
0)
1"
b1001110110 ,
b1001110110 0
b11101101 -
b11101101 .
1+
#1896
0+
#1900
0$
0"
b11101110 -
b11101110 .
b1001110000 ,
b1001110000 0
1+
#1904
0+
#1908
0*
1)
1!
b1001101001 ,
b1001101001 0
b11101111 -
b11101111 .
1+
#1912
0+
#1916
0)
1"
b11110000 -
b11110000 .
b1001100011 ,
b1001100011 0
1+
#1920
0+
#1924
0#
1*
1)
1$
0"
b1001011101 ,
b1001011101 0
b11110001 -
b11110001 .
1+
#1928
0+
#1932
0)
1"
b11110010 -
b11110010 .
b1001010111 ,
b1001010111 0
1+
#1936
0+
#1940
0$
0"
b1001010001 ,
b1001010001 0
b11110011 -
b11110011 .
1+
#1944
0+
#1948
0*
1)
1"
b11110100 -
b11110100 .
b1001001011 ,
b1001001011 0
1+
#1952
0+
#1956
0)
1$
0"
0!
b1001000100 ,
b1001000100 0
b11110101 -
b11110101 .
1+
#1960
0+
#1964
0(
1#
1*
1)
1"
b11110110 -
b11110110 .
b1000111110 ,
b1000111110 0
1+
#1968
0+
#1972
0$
0"
b1000111000 ,
b1000111000 0
b11110111 -
b11110111 .
1+
#1976
0+
#1980
0)
1"
b11111000 -
b11111000 .
b1000110010 ,
b1000110010 0
1+
#1984
0+
#1988
0*
1)
1!
b1000101011 ,
b1000101011 0
b11111001 -
b11111001 .
1+
#1992
0+
#1996
0)
1$
0"
b11111010 -
b11111010 .
b1000100101 ,
b1000100101 0
1+
#2000
0+
#2004
0#
1*
1)
1"
b1000011111 ,
b1000011111 0
b11111011 -
b11111011 .
1+
#2008
0+
#2012
0$
0"
b11111100 -
b11111100 .
b1000011001 ,
b1000011001 0
1+
#2016
0+
#2020
0)
1"
0!
b1000010010 ,
b1000010010 0
b11111101 -
b11111101 .
1+
#2024
0+
#2028
0*
1)
1$
0"
b11111110 -
b11111110 .
b1000001100 ,
b1000001100 0
1+
#2032
0+
#2036
0)
1"
b1000000110 ,
b1000000110 0
b11111111 -
b11111111 .
1+
#2040
0+
#2044
0$
0"
b100000000 -
b100000000 .
b1000000000 ,
b1000000000 0
1+
#2048
0+
#2052
b100000001 -
b100000001 .
1+
#2056
0+
